{"content":[{"id":"9b0ded8","elType":"container","settings":{"flex_direction":"row","flex_align_items":"stretch","flex_gap":{"size":10,"column":"10","row":"10","unit":"px"},"background_color":"#ffffff","padding":{"unit":"%","top":"4","right":"0","bottom":"4","left":"0","isLinked":false},"padding_tablet":{"unit":"%","top":"4","right":"4","bottom":"4","left":"4","isLinked":false},"padding_mobile":{"unit":"%","top":"4","right":"4","bottom":"4","left":"4","isLinked":true},"animation":"fadeIn"},"elements":[{"id":"dcdd02a","elType":"container","settings":{"_column_size":100,"width":{"size":null,"unit":"%"},"content_width":"full","padding":{"unit":"px","top":"0","right":"0","bottom":"0","left":"0","isLinked":true}},"elements":[{"id":"6c2ace2","elType":"container","settings":{"content_width":"full","animation":"fadeIn","animation_duration":"slow","structure":"20","margin":{"unit":"px","top":"0","right":"0","bottom":"0","left":"0","isLinked":false},"padding_mobile":{"unit":"px","top":"0","right":"20","bottom":"0","left":"20","isLinked":false},"flex_direction":"row","flex_align_items":"stretch","flex_gap":{"size":50,"column":"50","row":"50","unit":"px","isLinked":true},"flex_direction_tablet":"column","padding":{"unit":"px","top":"0","right":"0","bottom":"0","left":"0","isLinked":true}},"elements":[{"id":"ce1e6c0","elType":"container","settings":{"_column_size":50,"width":{"size":null,"unit":"%"},"flex_gap":{"size":0,"column":"0","row":"0","unit":"px"},"width_tablet":{"size":100,"unit":"%"},"width_mobile":{"size":100,"unit":"%"},"padding_mobile":{"unit":"px","top":"0","right":"0","bottom":"0","left":"0","isLinked":true},"align":"center","content_width":"full","flex_direction":"column","flex_justify_content":"center","flex_align_items":"center","padding":{"unit":"px","top":"0","right":"0","bottom":"0","left":"0","isLinked":true},"padding_tablet":{"unit":"%","top":"0","right":"8","bottom":"0","left":"8","isLinked":false}},"elements":[{"id":"19970b7","elType":"widget","settings":{"image":{"id":20483,"url":"{{ESELE_UPLOADS_URL}}\/2023\/09\/houzez-placeholder.png","alt":"","source":"library","size":""},"image_size":"custom","image_custom_dimension":{"width":"256","height":"256"},"align":"center","_margin":{"unit":"px","top":"0","right":"0","bottom":"20","left":"0","isLinked":false},"_element_width":"initial","_element_custom_width":{"unit":"px","size":200,"sizes":[]},"_animation":"fadeIn","animation_duration":"slow","width_tablet":{"unit":"%","size":65,"sizes":[]},"width_mobile":{"unit":"%","size":50,"sizes":[]},"image_border_radius":{"unit":"%","top":"50","right":"50","bottom":"50","left":"50","isLinked":true},"image_border_radius_tablet":{"unit":"%","top":"","right":"","bottom":"","left":"","isLinked":true},"image_border_radius_mobile":{"unit":"%","top":"","right":"","bottom":"","left":"","isLinked":true}},"elements":[],"widgetType":"image","htmlCache":"\t\t\t\t\t\t\t\t\t\t\t\t\t<img src=\"{{ESELE_UPLOADS_URL}}\/elementor\/thumbs\/houzez-placeholder-qxcrdwn440lx8m6m5l39xndf7irg9k6fnr3gfb8g00.png\" title=\"houzez-placeholder\" alt=\"houzez-placeholder\" loading=\"lazy\" \/>\t\t\t\t\t\t\t\t\t\t\t\t\t"},{"id":"ce04503","elType":"widget","settings":{"title":"Lorem ipsum dolor sit amet, consectetur adipiscing elit, sed dapibus enim.","typography_typography":"custom","typography_font_size":{"unit":"px","size":34,"sizes":[]},"typography_font_weight":"400","_margin":{"unit":"%","top":"0","right":"16","bottom":"5","left":"16","isLinked":false},"_animation":"fadeIn","animation_duration":"slow","align_mobile":"center","typography_font_size_mobile":{"unit":"px","size":27,"sizes":[]},"typography_font_size_tablet":{"unit":"px","size":30,"sizes":[]},"_margin_tablet":{"unit":"px","top":"0","right":"0","bottom":"30","left":"0","isLinked":false},"typography_line_height":{"unit":"em","size":1.5,"sizes":[]},"typography_letter_spacing":{"unit":"px","size":-0.5,"sizes":[]},"align":"center","typography_font_family":"Times New Roman","typography_font_style":"italic","typography_line_height_mobile":{"unit":"em","size":1.3,"sizes":[]}},"elements":[],"widgetType":"heading","htmlCache":"\t\t\t<h2 class=\"elementor-heading-title elementor-size-default\">Lorem ipsum dolor sit amet, consectetur adipiscing elit, sed dapibus enim.<\/h2>\t\t"},{"id":"384431d","elType":"widget","settings":{"text":"View More","align":"center","size":"md","typography_typography":"custom","typography_font_size":{"unit":"px","size":13,"sizes":[]},"typography_text_transform":"uppercase","typography_line_height":{"unit":"em","size":1.5,"sizes":[]},"typography_letter_spacing":{"unit":"px","size":5,"sizes":[]},"background_color":"#1B1F2D00","hover_color":"#78DAFF","border_width":{"unit":"px","top":"1","right":"1","bottom":"1","left":"1","isLinked":true},"border_radius":{"unit":"px","top":"0","right":"0","bottom":"0","left":"0","isLinked":true},"typography_font_weight":"700","button_text_color":"#00AEEF","border_color":"#1B1F2D","link":{"url":"https:\/\/demo26.houzez.co\/mls-search\/","is_external":"","nofollow":"","custom_attributes":""},"selected_icon":{"value":"fas fa-long-arrow-alt-right","library":"fa-solid"},"icon_align":"right","text_padding":{"unit":"px","top":"0","right":"0","bottom":"0","left":"0","isLinked":false},"align_tablet":"center","_animation":"fadeIn","animation_duration":"slow"},"elements":[],"widgetType":"button","htmlCache":"\t\t\t\t\t\t\t\t<a class=\"elementor-button elementor-button-link elementor-size-md\" href=\"https:\/\/demo26.houzez.co\/mls-search\/\">\n\t\t\t\t\t\t<span class=\"elementor-button-content-wrapper\">\n\t\t\t\t\t\t<span class=\"elementor-button-icon\">\n\t\t\t\t<svg aria-hidden=\"true\" class=\"e-font-icon-svg e-fas-long-arrow-alt-right\" viewBox=\"0 0 448 512\" xmlns=\"http:\/\/www.w3.org\/2000\/svg\"><path d=\"M313.941 216H12c-6.627 0-12 5.373-12 12v56c0 6.627 5.373 12 12 12h301.941v46.059c0 21.382 25.851 32.09 40.971 16.971l86.059-86.059c9.373-9.373 9.373-24.569 0-33.941l-86.059-86.059c-15.119-15.119-40.971-4.411-40.971 16.971V216z\"><\/path><\/svg>\t\t\t<\/span>\n\t\t\t\t\t\t\t\t\t<span class=\"elementor-button-text\">View More<\/span>\n\t\t\t\t\t<\/span>\n\t\t\t\t\t<\/a>\n\t\t\t\t\t\t"}],"isInner":true},{"id":"efb145f","elType":"container","settings":{"_column_size":50,"width":{"size":null,"unit":"%"},"flex_gap":{"size":30,"column":"30","row":"30","unit":"px","isLinked":true},"width_tablet":{"size":100,"unit":"%"},"flex_gap_tablet":{"size":30,"column":"30","row":"30","unit":"px","isLinked":true},"padding":{"unit":"px","top":"0","right":"0","bottom":"0","left":"0","isLinked":true},"padding_tablet":{"unit":"px","top":"0","right":"0","bottom":"0","left":"0","isLinked":true},"padding_mobile":{"unit":"px","top":"0","right":"0","bottom":"0","left":"0","isLinked":true},"content_width":"full","flex_gap_mobile":{"column":"30","row":"30","isLinked":true,"unit":"px","size":30}},"elements":[{"id":"889a4a9","elType":"widget","settings":{"selected_icon":{"value":"far fa-check-circle","library":"fa-regular"},"title_text":"Lorem ipsum dolor sit amet","description_text":"Integer ultrices lacus est, eu efficitur mauris rutrum eget. Duis malesuada ullamcorper tempus. Quisque accumsan pretium est. Aenean elit ipsum, porta nec efficitur eget, ultrices.","position":"left","icon_space":{"unit":"px","size":20,"sizes":[]},"icon_size":{"unit":"px","size":32,"sizes":[]},"title_typography_typography":"custom","title_typography_font_size":{"unit":"px","size":18,"sizes":[]},"title_typography_font_weight":"600","title_typography_line_height":{"unit":"em","size":1.8,"sizes":[]},"description_typography_typography":"custom","description_typography_font_weight":"300","description_typography_line_height":{"unit":"em","size":"","sizes":[]},"_animation":"fadeIn","animation_duration":"slow","primary_color":"#00AEEF"},"elements":[],"widgetType":"icon-box","htmlCache":"\t\t\t\t\t<div class=\"elementor-icon-box-wrapper\">\n\n\t\t\t\t\t\t<div class=\"elementor-icon-box-icon\">\n\t\t\t\t<span  class=\"elementor-icon\">\n\t\t\t\t<svg aria-hidden=\"true\" class=\"e-font-icon-svg e-far-check-circle\" viewBox=\"0 0 512 512\" xmlns=\"http:\/\/www.w3.org\/2000\/svg\"><path d=\"M256 8C119.033 8 8 119.033 8 256s111.033 248 248 248 248-111.033 248-248S392.967 8 256 8zm0 48c110.532 0 200 89.451 200 200 0 110.532-89.451 200-200 200-110.532 0-200-89.451-200-200 0-110.532 89.451-200 200-200m140.204 130.267l-22.536-22.718c-4.667-4.705-12.265-4.736-16.97-.068L215.346 303.697l-59.792-60.277c-4.667-4.705-12.265-4.736-16.97-.069l-22.719 22.536c-4.705 4.667-4.736 12.265-.068 16.971l90.781 91.516c4.667 4.705 12.265 4.736 16.97.068l172.589-171.204c4.704-4.668 4.734-12.266.067-16.971z\"><\/path><\/svg>\t\t\t\t<\/span>\n\t\t\t<\/div>\n\t\t\t\n\t\t\t\t\t\t<div class=\"elementor-icon-box-content\">\n\n\t\t\t\t\t\t\t\t\t<h3 class=\"elementor-icon-box-title\">\n\t\t\t\t\t\t<span  >\n\t\t\t\t\t\t\tLorem ipsum dolor sit amet\t\t\t\t\t\t<\/span>\n\t\t\t\t\t<\/h3>\n\t\t\t\t\n\t\t\t\t\t\t\t\t\t<p class=\"elementor-icon-box-description\">\n\t\t\t\t\t\tInteger ultrices lacus est, eu efficitur mauris rutrum eget. Duis malesuada ullamcorper tempus. Quisque accumsan pretium est. Aenean elit ipsum, porta nec efficitur eget, ultrices.\t\t\t\t\t<\/p>\n\t\t\t\t\n\t\t\t<\/div>\n\t\t\t\n\t\t<\/div>\n\t\t\t\t"},{"id":"b6f04ac","elType":"widget","settings":{"selected_icon":{"value":"far fa-check-circle","library":"fa-regular"},"title_text":"Lorem ipsum dolor sit amet","description_text":"Integer ultrices lacus est, eu efficitur mauris rutrum eget. Duis malesuada ullamcorper tempus. Quisque accumsan pretium est. Aenean elit ipsum, porta nec efficitur eget, ultrices.","position":"left","icon_space":{"unit":"px","size":20,"sizes":[]},"icon_size":{"unit":"px","size":32,"sizes":[]},"title_typography_typography":"custom","title_typography_font_size":{"unit":"px","size":18,"sizes":[]},"title_typography_font_weight":"600","title_typography_line_height":{"unit":"em","size":1.8,"sizes":[]},"description_typography_typography":"custom","description_typography_font_weight":"300","description_typography_line_height":{"unit":"em","size":"","sizes":[]},"_animation":"fadeIn","animation_duration":"slow","primary_color":"#00AEEF"},"elements":[],"widgetType":"icon-box","htmlCache":"\t\t\t\t\t<div class=\"elementor-icon-box-wrapper\">\n\n\t\t\t\t\t\t<div class=\"elementor-icon-box-icon\">\n\t\t\t\t<span  class=\"elementor-icon\">\n\t\t\t\t<svg aria-hidden=\"true\" class=\"e-font-icon-svg e-far-check-circle\" viewBox=\"0 0 512 512\" xmlns=\"http:\/\/www.w3.org\/2000\/svg\"><path d=\"M256 8C119.033 8 8 119.033 8 256s111.033 248 248 248 248-111.033 248-248S392.967 8 256 8zm0 48c110.532 0 200 89.451 200 200 0 110.532-89.451 200-200 200-110.532 0-200-89.451-200-200 0-110.532 89.451-200 200-200m140.204 130.267l-22.536-22.718c-4.667-4.705-12.265-4.736-16.97-.068L215.346 303.697l-59.792-60.277c-4.667-4.705-12.265-4.736-16.97-.069l-22.719 22.536c-4.705 4.667-4.736 12.265-.068 16.971l90.781 91.516c4.667 4.705 12.265 4.736 16.97.068l172.589-171.204c4.704-4.668 4.734-12.266.067-16.971z\"><\/path><\/svg>\t\t\t\t<\/span>\n\t\t\t<\/div>\n\t\t\t\n\t\t\t\t\t\t<div class=\"elementor-icon-box-content\">\n\n\t\t\t\t\t\t\t\t\t<h3 class=\"elementor-icon-box-title\">\n\t\t\t\t\t\t<span  >\n\t\t\t\t\t\t\tLorem ipsum dolor sit amet\t\t\t\t\t\t<\/span>\n\t\t\t\t\t<\/h3>\n\t\t\t\t\n\t\t\t\t\t\t\t\t\t<p class=\"elementor-icon-box-description\">\n\t\t\t\t\t\tInteger ultrices lacus est, eu efficitur mauris rutrum eget. Duis malesuada ullamcorper tempus. Quisque accumsan pretium est. Aenean elit ipsum, porta nec efficitur eget, ultrices.\t\t\t\t\t<\/p>\n\t\t\t\t\n\t\t\t<\/div>\n\t\t\t\n\t\t<\/div>\n\t\t\t\t"},{"id":"3ae1db1","elType":"widget","settings":{"selected_icon":{"value":"far fa-check-circle","library":"fa-regular"},"title_text":"Lorem ipsum dolor sit amet","description_text":"Integer ultrices lacus est, eu efficitur mauris rutrum eget. Duis malesuada ullamcorper tempus. Quisque accumsan pretium est. Aenean elit ipsum, porta nec efficitur eget, ultrices.","position":"left","icon_space":{"unit":"px","size":20,"sizes":[]},"icon_size":{"unit":"px","size":32,"sizes":[]},"title_typography_typography":"custom","title_typography_font_size":{"unit":"px","size":18,"sizes":[]},"title_typography_font_weight":"600","title_typography_line_height":{"unit":"em","size":1.8,"sizes":[]},"description_typography_typography":"custom","description_typography_font_weight":"300","description_typography_line_height":{"unit":"em","size":"","sizes":[]},"_animation":"fadeIn","animation_duration":"slow","primary_color":"#00AEEF"},"elements":[],"widgetType":"icon-box","htmlCache":"\t\t\t\t\t<div class=\"elementor-icon-box-wrapper\">\n\n\t\t\t\t\t\t<div class=\"elementor-icon-box-icon\">\n\t\t\t\t<span  class=\"elementor-icon\">\n\t\t\t\t<svg aria-hidden=\"true\" class=\"e-font-icon-svg e-far-check-circle\" viewBox=\"0 0 512 512\" xmlns=\"http:\/\/www.w3.org\/2000\/svg\"><path d=\"M256 8C119.033 8 8 119.033 8 256s111.033 248 248 248 248-111.033 248-248S392.967 8 256 8zm0 48c110.532 0 200 89.451 200 200 0 110.532-89.451 200-200 200-110.532 0-200-89.451-200-200 0-110.532 89.451-200 200-200m140.204 130.267l-22.536-22.718c-4.667-4.705-12.265-4.736-16.97-.068L215.346 303.697l-59.792-60.277c-4.667-4.705-12.265-4.736-16.97-.069l-22.719 22.536c-4.705 4.667-4.736 12.265-.068 16.971l90.781 91.516c4.667 4.705 12.265 4.736 16.97.068l172.589-171.204c4.704-4.668 4.734-12.266.067-16.971z\"><\/path><\/svg>\t\t\t\t<\/span>\n\t\t\t<\/div>\n\t\t\t\n\t\t\t\t\t\t<div class=\"elementor-icon-box-content\">\n\n\t\t\t\t\t\t\t\t\t<h3 class=\"elementor-icon-box-title\">\n\t\t\t\t\t\t<span  >\n\t\t\t\t\t\t\tLorem ipsum dolor sit amet\t\t\t\t\t\t<\/span>\n\t\t\t\t\t<\/h3>\n\t\t\t\t\n\t\t\t\t\t\t\t\t\t<p class=\"elementor-icon-box-description\">\n\t\t\t\t\t\tInteger ultrices lacus est, eu efficitur mauris rutrum eget. Duis malesuada ullamcorper tempus. Quisque accumsan pretium est. Aenean elit ipsum, porta nec efficitur eget, ultrices.\t\t\t\t\t<\/p>\n\t\t\t\t\n\t\t\t<\/div>\n\t\t\t\n\t\t<\/div>\n\t\t\t\t"}],"isInner":true}],"isInner":true}],"isInner":true}],"isInner":false}],"served_at":"2026-05-26 12:21:09"}