{"content":[{"id":"7d24baf","elType":"container","settings":{"min_height":{"size":"","unit":"vh"},"structure":"20","background_background":"classic","content_position":"middle","background_color_b":"#001c51","background_color_b_stop":{"unit":"%","size":80,"sizes":[]},"background_image":{"id":20740,"url":"{{ESELE_UPLOADS_URL}}\/2016\/02\/houzez-placeholder.png","alt":"","source":"library","size":""},"background_position":"center center","background_repeat":"no-repeat","background_size":"cover","background_overlay_background":"classic","background_overlay_color":"#00000099","background_overlay_color_b":"#001c51","background_overlay_opacity":{"unit":"px","size":1,"sizes":[]},"background_position_mobile":"bottom center","background_repeat_mobile":"no-repeat","background_size_mobile":"cover","flex_direction":"row","flex_align_items":"center","flex_gap":{"size":50,"column":"50","row":"50","unit":"px","isLinked":true},"padding":{"unit":"%","top":"8","right":"8","bottom":"8","left":"8","isLinked":true},"padding_tablet":{"unit":"%","top":"","right":"","bottom":"","left":"","isLinked":true},"padding_mobile":{"unit":"%","top":"","right":"","bottom":"","left":"","isLinked":true}},"elements":[{"id":"66e3840","elType":"container","settings":{"_column_size":50,"width":{"size":50,"unit":"%"},"width_tablet":{"size":50,"unit":"%"},"padding_tablet":{"unit":"px","top":"30","right":"30","bottom":"30","left":"30","isLinked":true},"content_width":"full","padding":{"unit":"px","top":"0","right":"0","bottom":"0","left":"0","isLinked":true}},"elements":[{"id":"7e6ac6b","elType":"widget","settings":{"hz_section_title":"Property Title","hz_section_subtitle":"Miami Beach, FL","section_title_typography_typography":"custom","section_title_typography_font_family":"","section_title_typography_font_size":{"unit":"px","size":50,"sizes":[]},"section_title_typography_font_weight":"700","section_subtitle_typography_typography":"custom","section_subtitle_typography_font_family":"Nunito","section_subtitle_typography_font_size":{"unit":"px","size":25,"sizes":[]},"section_subtitle_typography_font_weight":"100","houzez_section_title_align":"left","houzez_section_title_color":"#FFFFFF","houzez_section_subtitle_color":"#00AEFF","section_title_typography_line_height":{"unit":"em","size":1.3,"sizes":[]},"section_title_typography_letter_spacing":{"unit":"px","size":-0.5,"sizes":[]},"section_subtitle_typography_line_height":{"unit":"em","size":1.3,"sizes":[]},"homey_main_title_spacing":{"unit":"px","size":15,"sizes":[]},"homey_subtitle_spacing":{"unit":"px","size":0,"sizes":[]},"houzez_section_title_margin_bottom":{"unit":"px","size":0,"sizes":[]},"section_title_typography_font_size_mobile":{"unit":"px","size":30,"sizes":[]},"houzez_section_title_margin_bottom_mobile":{"unit":"px","size":0,"sizes":[]}},"elements":[],"widgetType":"houzez_elementor_section_title","htmlCache":"\t\t<div class=\"elementor-widget-container\">\n\t\t\t\t\t            <div class=\"houzez_section_title_wrap section-title-module\">\n                                    <h2 class=\"houzez_section_title\">Property Title<\/h2>\n                \n                                    <p class=\"houzez_section_subtitle\">Miami Beach, FL<\/p>\n                            <\/div>\n            \t\t\t\t<\/div>\n\t\t"},{"id":"7455729","elType":"widget","settings":{"width":{"unit":"%","size":10,"sizes":[]},"text":"Divider","color":"#00AEFF","weight":{"unit":"px","size":2,"sizes":[]},"gap":{"unit":"px","size":2,"sizes":[]},"align":"left","_margin":{"unit":"px","top":"10","right":"0","bottom":"10","left":"0","isLinked":false}},"elements":[],"widgetType":"divider","htmlCache":"\t\t\t\t\t<div class=\"elementor-divider\">\n\t\t\t<span class=\"elementor-divider-separator\">\n\t\t\t\t\t\t<\/span>\n\t\t<\/div>\n\t\t\t\t"},{"id":"2cb0ac4","elType":"widget","settings":{"selected_icon":{"value":{"id":"315","url":"{{ESELE_UPLOADS_URL}}\/2023\/08\/eco-house.svg"},"library":"svg"},"title_text":"Lorem ipsum ","description_text":"","position":"left","title_size":"div","primary_color":"#00AEFF","icon_space":{"unit":"px","size":20,"sizes":[]},"icon_size":{"unit":"px","size":30,"sizes":[]},"text_align":"left","title_color":"#ffffff","title_typography_typography":"custom","title_typography_font_size":{"unit":"px","size":18,"sizes":[]},"description_color":"#ffffff","description_typography_typography":"custom","description_typography_font_size":{"unit":"px","size":24,"sizes":[]},"icon_space_mobile":{"unit":"px","size":0,"sizes":[]},"text_align_mobile":"left","title_bottom_space_mobile":{"unit":"px","size":0,"sizes":[]},"_margin_mobile":{"unit":"px","top":"0","right":"0","bottom":"0","left":"0","isLinked":true},"_animation":"fadeIn","_animation_delay":600,"title_typography_font_family":"Nunito","title_typography_line_height":{"unit":"em","size":1.7,"sizes":[]}},"elements":[],"widgetType":"icon-box","htmlCache":"\t\t\t\t\t<div class=\"elementor-icon-box-wrapper\">\n\n\t\t\t\t\t\t<div class=\"elementor-icon-box-icon\">\n\t\t\t\t<span  class=\"elementor-icon\">\n\t\t\t\t<svg xmlns=\"http:\/\/www.w3.org\/2000\/svg\" xmlns:xlink=\"http:\/\/www.w3.org\/1999\/xlink\" id=\"Regular\" x=\"0px\" y=\"0px\" viewBox=\"0 0 24 24\" style=\"enable-background:new 0 0 24 24;\" xml:space=\"preserve\"><title>eco-house<\/title><g>\t<path d=\"M12.762,23.499c-0.097,0-0.193-0.019-0.284-0.056c-0.186-0.076-0.33-0.219-0.408-0.404s-0.078-0.389-0.002-0.574   c0.369-0.902,0.794-1.716,1.264-2.422c-0.776-1.124-1.092-2.25-0.914-3.273c0.187-1.073,0.899-1.988,2.061-2.645   c1.414-0.738,2.994-1.124,4.58-1.124c1.519,0,3.036,0.356,4.388,1.03c0.203,0.101,0.347,0.285,0.397,0.505   c0.05,0.22-0.001,0.448-0.139,0.627c-0.407,0.523-0.694,1.477-0.998,2.486c-0.681,2.261-1.613,5.356-4.926,5.659   c-0.099,0.009-0.197,0.013-0.293,0.013c-1.548,0-2.637-1.12-3.225-1.935c-0.293,0.5-0.564,1.052-0.808,1.647   C13.341,23.316,13.068,23.499,12.762,23.499z M15.195,20.064c0.255,0.439,1.117,1.757,2.298,1.757c0.05,0,0.101-0.002,0.152-0.007   c2.306-0.211,2.948-2.342,3.627-4.598c0.237-0.787,0.462-1.535,0.765-2.169c-0.95-0.363-1.951-0.547-2.98-0.547   c-1.343,0-2.678,0.326-3.861,0.943c-0.75,0.425-1.19,0.959-1.299,1.584c-0.09,0.517,0.055,1.12,0.422,1.763   c1.484-1.587,2.817-1.796,2.974-1.815c0.032-0.004,0.062-0.006,0.092-0.006c0.378,0,0.698,0.283,0.745,0.657   c0.051,0.408-0.24,0.783-0.647,0.836l0,0c0.001,0-0.551,0.095-1.29,0.65C15.851,19.368,15.516,19.687,15.195,20.064z\"><\/path>\t<path d=\"M5.385,20.5c-1.241,0-2.25-1.009-2.25-2.25v-7.5c0-0.414,0.336-0.75,0.75-0.75s0.75,0.336,0.75,0.75v7.5   c0,0.414,0.336,0.75,0.75,0.75h3.75c0.414,0,0.75,0.336,0.75,0.75s-0.336,0.75-0.75,0.75H5.385z\"><\/path>\t<path d=\"M0.885,10c-0.221,0-0.43-0.097-0.573-0.266C0.183,9.581,0.121,9.387,0.138,9.188c0.017-0.2,0.11-0.381,0.263-0.51   l9.75-8.25c0.135-0.114,0.307-0.177,0.484-0.177s0.349,0.063,0.485,0.178l9.75,8.25c0.153,0.129,0.246,0.311,0.263,0.51   c0.017,0.2-0.045,0.394-0.175,0.547C20.815,9.903,20.606,10,20.385,10l0,0c-0.177,0-0.349-0.063-0.484-0.177l-9.266-7.84   l-9.266,7.84C1.234,9.937,1.062,10,0.885,10z\"><\/path>\t<path d=\"M18.885,5.5c-0.414,0-0.75-0.336-0.75-0.75v-1.5c0-0.414-0.336-0.75-0.75-0.75h-1.5c-0.414,0-0.75-0.336-0.75-0.75   S15.471,1,15.885,1h1.5c1.241,0,2.25,1.009,2.25,2.25v1.5C19.635,5.163,19.299,5.5,18.885,5.5z\"><\/path><\/g><\/svg>\t\t\t\t<\/span>\n\t\t\t<\/div>\n\t\t\t\n\t\t\t\t\t\t<div class=\"elementor-icon-box-content\">\n\n\t\t\t\t\t\t\t\t\t<div class=\"elementor-icon-box-title\">\n\t\t\t\t\t\t<span  >\n\t\t\t\t\t\t\tLorem ipsum \t\t\t\t\t\t<\/span>\n\t\t\t\t\t<\/div>\n\t\t\t\t\n\t\t\t\t\n\t\t\t<\/div>\n\t\t\t\n\t\t<\/div>\n\t\t\t\t"},{"id":"b3b9e5d","elType":"widget","settings":{"selected_icon":{"value":{"id":"316","url":"{{ESELE_UPLOADS_URL}}\/2023\/08\/real-estate-action-building-check.svg"},"library":"svg"},"title_text":"Maecenas eget ante","description_text":"","position":"left","title_size":"div","primary_color":"#00AEFF","icon_space":{"unit":"px","size":20,"sizes":[]},"icon_size":{"unit":"px","size":30,"sizes":[]},"text_align":"left","title_color":"#ffffff","title_typography_typography":"custom","title_typography_font_size":{"unit":"px","size":18,"sizes":[]},"description_color":"#ffffff","description_typography_typography":"custom","description_typography_font_size":{"unit":"px","size":24,"sizes":[]},"description_typography_font_weight":"300","icon_space_mobile":{"unit":"px","size":0,"sizes":[]},"text_align_mobile":"left","_margin_mobile":{"unit":"px","top":"0","right":"0","bottom":"0","left":"0","isLinked":true},"_animation":"fadeIn","_animation_delay":600,"title_bottom_space_mobile":{"unit":"px","size":0,"sizes":[]},"title_typography_font_family":"Nunito","title_typography_line_height":{"unit":"em","size":1.7,"sizes":[]}},"elements":[],"widgetType":"icon-box","htmlCache":"\t\t\t\t\t<div class=\"elementor-icon-box-wrapper\">\n\n\t\t\t\t\t\t<div class=\"elementor-icon-box-icon\">\n\t\t\t\t<span  class=\"elementor-icon\">\n\t\t\t\t<svg xmlns=\"http:\/\/www.w3.org\/2000\/svg\" xmlns:xlink=\"http:\/\/www.w3.org\/1999\/xlink\" id=\"Regular\" x=\"0px\" y=\"0px\" viewBox=\"0 0 24 24\" style=\"enable-background:new 0 0 24 24;\" xml:space=\"preserve\"><title>real-estate-action-building-check<\/title><g>\t<path d=\"M0.75,24C0.336,24,0,23.663,0,23.25v-12C0,10.009,1.009,9,2.25,9h3V5.77c0.002-0.601,0.373-1.154,0.925-1.383L7.5,3.701   v-2.95c0-0.414,0.336-0.75,0.75-0.75S9,0.337,9,0.751v2.174l5.392-2.791c0.026-0.014,0.053-0.026,0.081-0.036   c0.167-0.063,0.343-0.095,0.521-0.096c0.83,0,1.503,0.671,1.506,1.496V8.25C16.5,8.663,16.164,9,15.75,9H12   c-0.414,0-0.75-0.336-0.75-0.75S11.586,7.5,12,7.5h3V6h-1.5c-0.414,0-0.75-0.336-0.75-0.75S13.086,4.5,13.5,4.5H15V1.508   L6.832,5.736C6.804,5.75,6.778,5.762,6.75,5.772L6.75,9C7.991,9,9,10.009,9,11.25V22.5h0.75c0.414,0,0.75,0.336,0.75,0.75   S10.164,24,9.75,24H0.75z M7.5,22.5V11.25c0-0.414-0.336-0.75-0.75-0.75h-4.5c-0.414,0-0.75,0.336-0.75,0.75V12H3   c0.414,0,0.75,0.336,0.75,0.75S3.414,13.5,3,13.5H1.5V15h3c0.414,0,0.75,0.336,0.75,0.75S4.914,16.5,4.5,16.5h-3v6H7.5z\"><\/path>\t<path d=\"M17.25,24c-3.722,0-6.75-3.028-6.75-6.75s3.028-6.75,6.75-6.75S24,13.528,24,17.25S20.972,24,17.25,24z M17.25,12   C14.355,12,12,14.355,12,17.25s2.355,5.25,5.25,5.25s5.25-2.355,5.25-5.25S20.145,12,17.25,12z\"><\/path>\t<path d=\"M16.417,20.428c-0.328,0-0.64-0.104-0.902-0.302c-0.055-0.042-0.106-0.086-0.154-0.133l-1.503-1.503   c-0.142-0.142-0.22-0.33-0.22-0.53s0.078-0.389,0.22-0.53s0.33-0.22,0.53-0.22s0.389,0.078,0.53,0.22l1.5,1.5l2.906-3.874   c0.141-0.188,0.366-0.3,0.6-0.3c0.163,0,0.318,0.052,0.449,0.149c0.331,0.249,0.399,0.72,0.151,1.051l-2.905,3.873   C17.336,20.204,16.887,20.428,16.417,20.428z\"><\/path><\/g><\/svg>\t\t\t\t<\/span>\n\t\t\t<\/div>\n\t\t\t\n\t\t\t\t\t\t<div class=\"elementor-icon-box-content\">\n\n\t\t\t\t\t\t\t\t\t<div class=\"elementor-icon-box-title\">\n\t\t\t\t\t\t<span  >\n\t\t\t\t\t\t\tMaecenas eget ante\t\t\t\t\t\t<\/span>\n\t\t\t\t\t<\/div>\n\t\t\t\t\n\t\t\t\t\n\t\t\t<\/div>\n\t\t\t\n\t\t<\/div>\n\t\t\t\t"},{"id":"0c7ba44","elType":"widget","settings":{"selected_icon":{"value":{"url":"{{ESELE_UPLOADS_URL}}\/2023\/10\/streamline-icon-real-estate-favorite-house-rating@64x64.svg","id":18581},"library":"svg"},"title_text":"Maecenas eget ante","description_text":"","position":"left","title_size":"div","primary_color":"#00AEFF","icon_space":{"unit":"px","size":20,"sizes":[]},"icon_size":{"unit":"px","size":30,"sizes":[]},"text_align":"left","title_color":"#ffffff","title_typography_typography":"custom","title_typography_font_size":{"unit":"px","size":18,"sizes":[]},"description_color":"#ffffff","description_typography_typography":"custom","description_typography_font_size":{"unit":"px","size":24,"sizes":[]},"description_typography_font_weight":"300","icon_space_mobile":{"unit":"px","size":0,"sizes":[]},"text_align_mobile":"left","_margin_mobile":{"unit":"px","top":"0","right":"0","bottom":"0","left":"0","isLinked":true},"_animation":"fadeIn","_animation_delay":600,"title_bottom_space_mobile":{"unit":"px","size":0,"sizes":[]},"title_typography_font_family":"Nunito","title_typography_line_height":{"unit":"em","size":1.7,"sizes":[]}},"elements":[],"widgetType":"icon-box","htmlCache":"\t\t\t\t\t<div class=\"elementor-icon-box-wrapper\">\n\n\t\t\t\t\t\t<div class=\"elementor-icon-box-icon\">\n\t\t\t\t<span  class=\"elementor-icon\">\n\t\t\t\t<svg xmlns=\"http:\/\/www.w3.org\/2000\/svg\" xmlns:xlink=\"http:\/\/www.w3.org\/1999\/xlink\" xmlns:svgjs=\"http:\/\/svgjs.com\/svgjs\" viewBox=\"0 0 64 64\" width=\"64\" height=\"64\"><g transform=\"matrix(2.6666666666666665,0,0,2.6666666666666665,0,0)\"><path d=\"M12.531,1.076l1.248,2.457h2.127a.583.583,0,0,1,.419,1L14.373,6.452l1.081,2.485a.589.589,0,0,1-.839.736L12,8.2,9.385,9.673a.589.589,0,0,1-.839-.736L9.628,6.452,7.675,4.53a.583.583,0,0,1,.419-1h2.127L11.47,1.076A.594.594,0,0,1,12.531,1.076Z\" fill=\"none\" stroke=\"#409fff\" stroke-linecap=\"round\" stroke-linejoin=\"round\" stroke-width=\"1.5\"><\/path><path d=\"M5.25,2.25a.588.588,0,0,0-.53.326L3.471,5.033H1.344a.583.583,0,0,0-.419,1L2.878,7.952,1.8,10.437a.589.589,0,0,0,.839.736L5.25,9.7l.692.389\" fill=\"none\" stroke=\"#409fff\" stroke-linecap=\"round\" stroke-linejoin=\"round\" stroke-width=\"1.5\"><\/path><path d=\"M18.75,2.25a.59.59,0,0,1,.531.326l1.248,2.457h2.127a.583.583,0,0,1,.419,1L21.122,7.952,22.2,10.437a.589.589,0,0,1-.839.736L18.75,9.7l-.692.389\" fill=\"none\" stroke=\"#409fff\" stroke-linecap=\"round\" stroke-linejoin=\"round\" stroke-width=\"1.5\"><\/path><path d=\"M7.5,18.235v3.518a1.5,1.5,0,0,0,1.5,1.5h6a1.5,1.5,0,0,0,1.5-1.5V18.235\" fill=\"none\" stroke=\"#409fff\" stroke-linecap=\"round\" stroke-linejoin=\"round\" stroke-width=\"1.5\"><\/path><path d=\"M19.5,17.485,13,11.638a1.5,1.5,0,0,0-2.006,0L4.5,17.485\" fill=\"none\" stroke=\"#409fff\" stroke-linecap=\"round\" stroke-linejoin=\"round\" stroke-width=\"1.5\"><\/path><\/g><\/svg>\t\t\t\t<\/span>\n\t\t\t<\/div>\n\t\t\t\n\t\t\t\t\t\t<div class=\"elementor-icon-box-content\">\n\n\t\t\t\t\t\t\t\t\t<div class=\"elementor-icon-box-title\">\n\t\t\t\t\t\t<span  >\n\t\t\t\t\t\t\tMaecenas eget ante\t\t\t\t\t\t<\/span>\n\t\t\t\t\t<\/div>\n\t\t\t\t\n\t\t\t\t\n\t\t\t<\/div>\n\t\t\t\n\t\t<\/div>\n\t\t\t\t"}],"isInner":true},{"id":"aa85fc6","elType":"container","settings":{"_column_size":50,"width":{"size":37.891,"unit":"%"},"background_background":"classic","background_color":"#FFFFFF","margin_tablet":{"unit":"px","top":"0","right":"30","bottom":"0","left":"0","isLinked":false},"margin_mobile":{"unit":"px","top":"0","right":"20","bottom":"20","left":"20","isLinked":false},"padding":{"unit":"%","top":"4","right":"4","bottom":"4","left":"4","isLinked":true},"animation":"fadeIn","animation_delay":200,"margin":{"unit":"px","top":"0","right":"0","bottom":"0","left":"0","isLinked":false},"content_width":"full","padding_tablet":{"unit":"%","top":"","right":"","bottom":"","left":"","isLinked":true},"padding_mobile":{"unit":"%","top":"","right":"","bottom":"","left":"","isLinked":true}},"elements":[{"id":"eb1685e","elType":"widget","settings":{"hz_section_title":"Request Information","hz_section_subtitle":"This form is customizable and designed to work with EstateSite CRM","section_title_typography_typography":"custom","section_title_typography_font_family":"","section_title_typography_font_size":{"unit":"px","size":20,"sizes":[]},"section_subtitle_typography_typography":"custom","section_subtitle_typography_font_family":"","houzez_section_title_align":"left","houzez_section_title_color":"#000000","houzez_section_subtitle_color":"#7A7A7A","section_title_typography_font_weight":"700","section_subtitle_typography_font_weight":"100","homey_subtitle_spacing":{"unit":"px","size":0,"sizes":[]},"houzez_section_title_margin_bottom":{"unit":"px","size":0,"sizes":[]},"section_subtitle_typography_font_size":{"unit":"px","size":15,"sizes":[]}},"elements":[],"widgetType":"houzez_elementor_section_title","htmlCache":"\t\t<div class=\"elementor-widget-container\">\n\t\t\t\t\t            <div class=\"houzez_section_title_wrap section-title-module\">\n                                    <h2 class=\"houzez_section_title\">Request Information<\/h2>\n                \n                                    <p class=\"houzez_section_subtitle\">This form is customizable and designed to work with EstateSite CRM<\/p>\n                            <\/div>\n            \t\t\t\t<\/div>\n\t\t"},{"id":"7fbb7c7","elType":"widget","settings":{"form_name":"New Form","form_fields":[{"field_type":"name","field_label":"Name","placeholder":"Name","required":"true","width":"50","_id":"19a9b37"},{"field_type":"mobile","field_label":"Phone","placeholder":"Phone","required":"true","width":"50","_id":"9fe1a42"},{"field_type":"email","field_label":"Email","placeholder":"Email","required":"true","_id":"332f916"}],"show_labels":"","button_text":"Request","email_to":"hello@favethemes.com","email_subject":"New message from &quot;EstateSite&quot;","button_background_color":"#00AEFF","button_background_hover_color":"rgba(97, 206, 112, 0.76)","input_size":"md","gdpr_agreement":"yes","gdpr_label":"GDPR Agreement","gdpr_text":"I consent to having this website store my submitted information","button_size":"md","label_color":"#000000","field_text_color":"#000000","field_border_color":"#E6E6E6","field_gdpr_color":"#7A7A7A","gdpr_typography_typography":"custom","gdpr_typography_font_size":{"unit":"px","size":15,"sizes":[]},"gdpr_typography_line_height":{"unit":"em","size":1.7,"sizes":[]},"gdpr_required":"true","field_border_width":{"unit":"px","top":"2","right":"2","bottom":"2","left":"2","isLinked":true},"_margin":{"unit":"px","top":"0","right":"0","bottom":"-40","left":"0","isLinked":false}},"elements":[],"widgetType":"houzez_elementor_inquiry_form","htmlCache":"\t\t<div class=\"elementor-widget-container\">\n\t\t\t\t\t\n        <script type=\"application\/javascript\">\n            jQuery(document).bind(\"ready\", function () {\n                houzezValidateElementor(\"#houzez-form-7fbb7c7\" );\n            });\n        <\/script>\n\n\n        <form class=\"elementor-form houzez-ele-form-js\" id=\"houzez-form-7fbb7c7\" method=\"post\" name=\"New Form\" action=\"https:\/\/estatesite.example\/wp-admin\/admin-ajax.php\">\n            <input type=\"hidden\" name=\"form_id\" value=\"7fbb7c7\"\/>\n            <input type=\"hidden\" name=\"action\" value=\"houzez_ele_inquiry_form\" \/>\n            <input type=\"hidden\" name=\"source_link\" value=\"\" \/>\n            <input type=\"hidden\" name=\"lead_page_id\" value=\"0\" \/>\n            <input type=\"hidden\" name=\"is_estimation\" value=\"yes\" \/>\n            <input type=\"hidden\" name=\"webhook\" value=\"false\" \/>\n            <input type=\"hidden\" name=\"webhook_url\" value=\"\" \/>\n            <input type=\"hidden\" name=\"redirect_to\" value=\"\" \/>\n            <input type=\"hidden\" name=\"email_subject\" value=\"New message from &quot;EstateSite&quot;\" \/>\n            <input type=\"hidden\" name=\"google_recaptcha\" value=\"false\" \/>\n\n            <div class=\"elementor-form-fields-wrapper elementor-labels-above\">\n\n                                    <div class=\"elementor-field-group elementor-column form-group elementor-field-group-19a9b37 elementor-col-50 elementor-field-required\">\n                    <label for=\"form-field-19a9b37\" class=\"form-label elementor-field-label elementor-screen-only\">Name<\/label><input type=\"text\" name=\"name\" id=\"form-field-19a9b37\" class=\"elementor-field form-control elementor-size-md elementor-field-textual\" placeholder=\"Name\" title=\"* Name\" required=\"required\">                    <\/div>\n\n                                        <div class=\"elementor-field-group elementor-column form-group elementor-field-group-9fe1a42 elementor-col-50 elementor-field-required\">\n                    <label for=\"form-field-9fe1a42\" class=\"form-label elementor-field-label elementor-screen-only\">Phone<\/label><input type=\"text\" name=\"mobile\" id=\"form-field-9fe1a42\" class=\"elementor-field form-control elementor-size-md elementor-field-textual\" placeholder=\"Phone\" title=\"* Phone\" required=\"required\">                    <\/div>\n\n                                        <div class=\"elementor-field-group elementor-column form-group elementor-field-group-332f916 elementor-col-100 elementor-field-required\">\n                    <label for=\"form-field-332f916\" class=\"form-label elementor-field-label elementor-screen-only\">Email<\/label><input type=\"email\" name=\"email\" id=\"form-field-332f916\" class=\"elementor-field form-control elementor-size-md elementor-field-textual\" placeholder=\"Email\" title=\"* Email\" required=\"required\">                    <\/div>\n\n                    \n                    \n                                        <div class=\"form-group elementor-field-group elementor-col-100\">\n                        <label class=\"control control--checkbox m-0 \">\n                                                        <input required type=\"checkbox\" name=\"gdpr_agreement\" id=\"gdpr_agreement\" aria-required=\"true\">\n                            <span class=\"control__indicator\"><\/span>\n                                                        <div class=\"gdpr-text-wrap\">\n                            I consent to having this website store my submitted information                            <\/div>\n                            \n                        <\/label>\n                    <\/div><!-- form-group -->\n                    \n                    \n                    \n                    <div class=\"elementor-field-group elementor-column elementor-field-type-submit elementor-col-100\">\n                    <button type=\"submit\" class=\"houzez-submit-button houzez-contact-form-js elementor-button elementor-size-md\">\n                        <i class=\"houzez-loader-js houzez-hidden spinner-border spinner-border-sm\"><\/i>\n                                                    Request                                            <\/button>\n                <\/div>\n            <\/div><!-- End wrapper-->\n            <br\/>\n            <div class=\"ele-form-messages\"><\/div>\n            <div class=\"error-container\"><\/div>\n\n        <\/form>\n\n    \t\t\t\t<\/div>\n\t\t"}],"isInner":true}],"isInner":false}],"served_at":"2026-05-26 12:22:55"}